geometa_grid
