Metadata-Version: 1.2
Name: girder-geospatial-grid
Version: 0.1.0
Summary: Support for grid data types in the girder-geospatial package
Home-page: https://github.com/OpenGeoscience/girder_geospatial
Maintainer: Kitware, Inc.
Maintainer-email: kitware@kitware.com
License: UNKNOWN
Platform: UNKNOWN
